[{"hashtag":"#iHeartBTS","href":"/trend/79837188"},{"hashtag":"#HappySuhoDay","href":"/trend/79837187"},{"hashtag":"#EuJáSabia","href":"/trend/79837186"},{"hashtag":"#Edicao18","href":"/trend/79837185"},{"hashtag":"#GOFIMO","href":"/trend/79837184"},{"hashtag":"#TiraMãoDoMeuEnem","href":"/trend/79837183"},{"hashtag":"#DirtIsHere","href":"/trend/79837182"},{"hashtag":"#Sub17noSportv","href":"/trend/79837181"},{"hashtag":"#KIMJUNCOTTONDAY","href":"/trend/79837180"},{"hashtag":"#TodaFormaDeAmar","href":"/trend/79837179"},{"hashtag":"#Graffite","href":"/trend/79837178"},{"hashtag":"#McDaleste","href":"/trend/79837177"},{"hashtag":"#AQueNaoPodiaAmar032","href":"/trend/79837176"},{"hashtag":"#BLACKPINKinMANCHESTER","href":"/trend/79837175"},{"hashtag":"#ADona037","href":"/trend/79837174"},{"hashtag":"#1stCartoonCrush","href":"/trend/79837173"},{"hashtag":"#VirgemNoEstadio","href":"/trend/79837172"},{"hashtag":"#BLABLAMTVHITS","href":"/trend/79837171"},{"hashtag":"#VoleiNoSporTV","href":"/trend/79837170"},{"hashtag":"Vítor Hugo","href":"/trend/79837169"},{"hashtag":"Cech","href":"/trend/79837168"},{"hashtag":"atílio","href":"/trend/79837167"},{"hashtag":"Beijos de Paris","href":"/trend/79837166"},{"hashtag":"Leno","href":"/trend/79837165"},{"hashtag":"Lugares","href":"/trend/79837164"},{"hashtag":"Bryan Ruiz","href":"/trend/79837163"},{"hashtag":"Margarida","href":"/trend/79837162"},{"hashtag":"Edir Macedo","href":"/trend/79837161"},{"hashtag":"Kevinho","href":"/trend/79837160"},{"hashtag":"Tirei Barraco","href":"/trend/79837159"},{"hashtag":"Flávia Pavanelli","href":"/trend/79837158"},{"hashtag":"Atlas Político","href":"/trend/79837157"},{"hashtag":"F de Flash","href":"/trend/79837156"},{"hashtag":"Ustra","href":"/trend/79837155"},{"hashtag":"Tarantino","href":"/trend/79837154"},{"hashtag":"Major Vitor Hugo","href":"/trend/79837153"},{"hashtag":"Djamila","href":"/trend/79837152"},{"hashtag":"Carlinhos e Lucas","href":"/trend/79837151"},{"hashtag":"Origin","href":"/trend/79837150"},{"hashtag":"Prêmio Camões","href":"/trend/79837149"},{"hashtag":"Cláudia","href":"/trend/79837148"},{"hashtag":"The Sims 4","href":"/trend/79837147"},{"hashtag":"#NordesteComBolsonaro","href":"/trend/79837146"},{"hashtag":"#carlu","href":"/trend/79837145"},{"hashtag":"#PrevidenciaAntiCrimeJa","href":"/trend/79837144"},{"hashtag":"Adão e Eva","href":"/trend/79837143"},{"hashtag":"Chico Buarque","href":"/trend/79837142"},{"hashtag":"#casamentocarlu","href":"/trend/79837141"},{"hashtag":"#OBMEP","href":"/trend/79837140"},{"hashtag":"Carlinhos Maia","href":"/trend/79837139"}]