[{"hashtag":"#voltacarlu","href":"/trend/80180692"},{"hashtag":"#Indy500","href":"/trend/80180691"},{"hashtag":"#FORxVAS","href":"/trend/80180690"},{"hashtag":"#Faustão","href":"/trend/80180689"},{"hashtag":"#colunadofla","href":"/trend/80180688"},{"hashtag":"#CORxSAO","href":"/trend/80180687"},{"hashtag":"#DomingaoDoFaustao","href":"/trend/80180686"},{"hashtag":"#Eliana","href":"/trend/80180685"},{"hashtag":"#ShowDosFamosos","href":"/trend/80180684"},{"hashtag":"#LGBTQunite","href":"/trend/80180683"},{"hashtag":"RESERVA","href":"/trend/80180682"},{"hashtag":"Esse Flamengo","href":"/trend/80180681"},{"hashtag":"Parede","href":"/trend/80180680"},{"hashtag":"Cueva","href":"/trend/80180679"},{"hashtag":"Sarrafiore","href":"/trend/80180678"},{"hashtag":"atlético paranaense","href":"/trend/80180677"},{"hashtag":"Rene","href":"/trend/80180676"},{"hashtag":"Roger Flores","href":"/trend/80180675"},{"hashtag":"Piris","href":"/trend/80180674"},{"hashtag":"Vitor Bueno","href":"/trend/80180673"},{"hashtag":"UFPR","href":"/trend/80180672"},{"hashtag":"ISSO AQUI É FLAMENGO","href":"/trend/80180671"},{"hashtag":"Yan Sasse","href":"/trend/80180670"},{"hashtag":"Tiago Nunes","href":"/trend/80180669"},{"hashtag":"Cuesta","href":"/trend/80180668"},{"hashtag":"Tomás Andrade","href":"/trend/80180667"},{"hashtag":"#BrasiINasRuas","href":"/trend/80180666"},{"hashtag":"#OrgulhoGado","href":"/trend/80180665"},{"hashtag":"Paulista","href":"/trend/80180664"},{"hashtag":"Lincoln","href":"/trend/80180663"},{"hashtag":"Gabigol","href":"/trend/80180662"},{"hashtag":"#BTSinAllianzParque","href":"/trend/80180661"},{"hashtag":"#BTSatAllianzParque_D2","href":"/trend/80180660"},{"hashtag":"Rodrygo","href":"/trend/80180659"},{"hashtag":"Odair","href":"/trend/80180658"},{"hashtag":"Lulu Santos","href":"/trend/80180657"},{"hashtag":"Pottker","href":"/trend/80180656"},{"hashtag":"O Flamengo","href":"/trend/80180655"},{"hashtag":"Renê","href":"/trend/80180654"},{"hashtag":"Athletico","href":"/trend/80180653"},{"hashtag":"Everton Ribeiro","href":"/trend/80180652"},{"hashtag":"Maracanã","href":"/trend/80180651"},{"hashtag":"Diego Alves","href":"/trend/80180650"},{"hashtag":"Rodinei","href":"/trend/80180649"},{"hashtag":"Arrascaeta","href":"/trend/80180648"},{"hashtag":"Bruno Henrique","href":"/trend/80180647"},{"hashtag":"#FLAxCAP","href":"/trend/80180646"},{"hashtag":"Cirino","href":"/trend/80180645"},{"hashtag":"Rodrigo Caio","href":"/trend/80180644"},{"hashtag":"Abel","href":"/trend/80180643"}]