[{"hashtag":"#VoltaPato","href":"/trend/73594840"},{"hashtag":"#EuropaLeagueFOXSports","href":"/trend/73594839"},{"hashtag":"#남준아_넌_나의_사랑_단_한_사랑","href":"/trend/73594838"},{"hashtag":"#HAPPYSOLARDAY","href":"/trend/73594837"},{"hashtag":"#BotafogoNaRedeTV","href":"/trend/73594836"},{"hashtag":"#BeYouWendy","href":"/trend/73594835"},{"hashtag":"#NovaPrevidencia","href":"/trend/73594834"},{"hashtag":"#BalançoGeralRJ","href":"/trend/73594833"},{"hashtag":"#ADO26NÃO","href":"/trend/73594832"},{"hashtag":"#NoTwitterEuSou","href":"/trend/73594831"},{"hashtag":"#majornaesl","href":"/trend/73594830"},{"hashtag":"#TeLoDije","href":"/trend/73594829"},{"hashtag":"#happywendyday","href":"/trend/73594828"},{"hashtag":"#BBB18","href":"/trend/73594827"},{"hashtag":"#AtardeESua","href":"/trend/73594826"},{"hashtag":"#SomosTodasEva","href":"/trend/73594825"},{"hashtag":"#Unpacked2019","href":"/trend/73594824"},{"hashtag":"#fsradiobrasil","href":"/trend/73594823"},{"hashtag":"#LoveYourPetDay","href":"/trend/73594822"},{"hashtag":"#goodluckliamrita","href":"/trend/73594821"},{"hashtag":"#SamsungUnpacked","href":"/trend/73594820"},{"hashtag":"#FofocalizandoNoSBT","href":"/trend/73594819"},{"hashtag":"#GalaxyUnpacked","href":"/trend/73594818"},{"hashtag":"#BRITS2019","href":"/trend/73594817"},{"hashtag":"Sansa Stark","href":"/trend/73594816"},{"hashtag":"PATRICIA NUNCA","href":"/trend/73594815"},{"hashtag":"Carol Dantas","href":"/trend/73594814"},{"hashtag":"BRIT Awards","href":"/trend/73594813"},{"hashtag":"Bruno Bianco","href":"/trend/73594812"},{"hashtag":"BBB 18","href":"/trend/73594811"},{"hashtag":"Tirei Nunca","href":"/trend/73594810"},{"hashtag":"Jesy","href":"/trend/73594809"},{"hashtag":"Guto Ferreira","href":"/trend/73594808"},{"hashtag":"PSOL","href":"/trend/73594807"},{"hashtag":"Lazio","href":"/trend/73594806"},{"hashtag":"Atlético de Madrid x Juventus","href":"/trend/73594805"},{"hashtag":"FGTS","href":"/trend/73594804"},{"hashtag":"Lucas Santos","href":"/trend/73594803"},{"hashtag":"DOCEIRA SIM","href":"/trend/73594802"},{"hashtag":"jorge","href":"/trend/73594801"},{"hashtag":"Fernanda Montenegro","href":"/trend/73594800"},{"hashtag":"Galaxy S10","href":"/trend/73594799"},{"hashtag":"NOPAU COM JALAPAO100LIMITES","href":"/trend/73594798"},{"hashtag":"Reforma da Previdência","href":"/trend/73594797"},{"hashtag":"#GloboInimigaDoBrasil","href":"/trend/73594796"},{"hashtag":"#SomosMIBR","href":"/trend/73594795"},{"hashtag":"#SamsungEvent","href":"/trend/73594794"},{"hashtag":"Galaxy Fold","href":"/trend/73594793"},{"hashtag":"#ReajaOuSuaPrevidênciaAcaba","href":"/trend/73594792"},{"hashtag":"#LittleMixAtTheBrits","href":"/trend/73594791"}]