[{"hashtag":"#estudioi","href":"/trend/81283294"},{"hashtag":"#EuToComTheIntercept","href":"/trend/81283293"},{"hashtag":"#CaminhosDoCoração61","href":"/trend/81283292"},{"hashtag":"#bbdebate","href":"/trend/81283291"},{"hashtag":"#PLN4VoteSim","href":"/trend/81283290"},{"hashtag":"#enigmaprimorico","href":"/trend/81283289"},{"hashtag":"#NamorarPraQueSe","href":"/trend/81283288"},{"hashtag":"#ThankYouNCT","href":"/trend/81283287"},{"hashtag":"#terminei","href":"/trend/81283286"},{"hashtag":"#SeInvadiremMeuWhats","href":"/trend/81283285"},{"hashtag":"#EuroNoSpace","href":"/trend/81283284"},{"hashtag":"#Frozen2","href":"/trend/81283283"},{"hashtag":"#PLN4Talkey","href":"/trend/81283282"},{"hashtag":"#14JVaiPararTudo","href":"/trend/81283281"},{"hashtag":"Link's Awakening","href":"/trend/81283280"},{"hashtag":"Tailandesas","href":"/trend/81283279"},{"hashtag":"Telephone","href":"/trend/81283278"},{"hashtag":"PES 2020","href":"/trend/81283277"},{"hashtag":"Lavelle","href":"/trend/81283276"},{"hashtag":"Lewandowski","href":"/trend/81283275"},{"hashtag":"Marco Reus","href":"/trend/81283274"},{"hashtag":"2ª Turma","href":"/trend/81283273"},{"hashtag":"Fundo Amazônia","href":"/trend/81283272"},{"hashtag":"Kai'sa","href":"/trend/81283271"},{"hashtag":"Banjo","href":"/trend/81283270"},{"hashtag":"Rapinoe","href":"/trend/81283269"},{"hashtag":"Eu e o Jungkook","href":"/trend/81283268"},{"hashtag":"Noruega e Alemanha","href":"/trend/81283267"},{"hashtag":"Roberto Fernandes","href":"/trend/81283266"},{"hashtag":"Adélio Bispo","href":"/trend/81283265"},{"hashtag":"BOTW","href":"/trend/81283264"},{"hashtag":"O Telegram","href":"/trend/81283263"},{"hashtag":"Smash","href":"/trend/81283262"},{"hashtag":"Breath of the Wild","href":"/trend/81283261"},{"hashtag":"Tortura","href":"/trend/81283260"},{"hashtag":"Hope Solo","href":"/trend/81283259"},{"hashtag":"animal crossing","href":"/trend/81283258"},{"hashtag":"Estônia","href":"/trend/81283257"},{"hashtag":"Switch","href":"/trend/81283256"},{"hashtag":"Emissoras de TV","href":"/trend/81283255"},{"hashtag":"Zelda","href":"/trend/81283254"},{"hashtag":"Atílio","href":"/trend/81283253"},{"hashtag":"Nintendo","href":"/trend/81283252"},{"hashtag":"#STFNaoSolteLula","href":"/trend/81283251"},{"hashtag":"#EuToComOMoro","href":"/trend/81283250"},{"hashtag":"Alex Morgan","href":"/trend/81283249"},{"hashtag":"#ElaJaSabia","href":"/trend/81283248"},{"hashtag":"#USATHA","href":"/trend/81283247"},{"hashtag":"Tailândia","href":"/trend/81283246"},{"hashtag":"#LibertemLula","href":"/trend/81283245"}]